card_component/__init__.py
card_component/frontend/build/asset-manifest.json
card_component/frontend/build/bootstrap.min.css
card_component/frontend/build/index.html
card_component/frontend/build/static/js/main.0bd99520.js
card_component/frontend/build/static/js/main.0bd99520.js.LICENSE.txt
card_component/frontend/build/static/js/main.0bd99520.js.map
card_component/frontend/build/static/js/main.1e267dda.js
card_component/frontend/build/static/js/main.1e267dda.js.LICENSE.txt
card_component/frontend/build/static/js/main.1e267dda.js.map
singletrack_ml_card_component-0.0.7.dist-info/LICENSE
singletrack_ml_card_component-0.0.7.dist-info/METADATA
singletrack_ml_card_component-0.0.7.dist-info/WHEEL
singletrack_ml_card_component-0.0.7.dist-info/top_level.txt
singletrack_ml_card_component-0.0.7.dist-info/RECORD
