Metadata-Version: 2.1
Name: singletrack-ml-card-component
Version: 0.0.7
Home-page: 
Author: 
Author-email: 
Requires-Python: >=3.8
License-File: LICENSE
Requires-Dist: streamlit (>=0.63)
